pyams_batching/__init__.py
pyams_batching/batch.py
pyams_batching/include.py
pyams_batching/interfaces.py
pyams_batching/subset.py
pyams_batching/doctests/README.rst
pyams_batching/doctests/subset.rst
pyams_batching/locales/pyams_batching.pot
pyams_batching/locales/fr/LC_MESSAGES/pyams_batching.po
pyams_batching/tests/__init__.py
pyams_batching/tests/test_utilsdocs.py
pyams_batching/tests/test_utilsdocstrings.py
pyams_batching-2.0.2.dist-info/LICENSE
pyams_batching-2.0.2.dist-info/METADATA
pyams_batching-2.0.2.dist-info/WHEEL
pyams_batching-2.0.2.dist-info/namespace_packages.txt
pyams_batching-2.0.2.dist-info/top_level.txt
pyams_batching-2.0.2.dist-info/RECORD
